[
  {
    "name": "Antônio Holanda",
    "rating": 4
  },
  {
    "name": "Genilson Medeiros",
    "rating": 4
  },
  {
    "name": "Hiago Lima",
    "rating": 3
  },
  {
    "name": "Iago Nóbrega",
    "rating": 3
  },
  {
    "name": "Ramon Kieveer",
    "rating": 3
  },
  {
    "name": "Lucas Willian",
    "rating": 3
  },
  {
    "name": "Mathews Lima",
    "rating": 3
  },
  {
    "name": "Adriano Nunes",
    "rating": 3
  },
  {
    "name": "Pedro Baruc",
    "rating": 5
  },
  {
    "name": "Giovanni",
    "rating": 3
  },
  {
    "name": "Jogador",
    "rating": 3
  },
  {
    "name": "Thiago Baruc",
    "rating": 4
  },
  {
    "name": "Matheus Glauber",
    "rating": 1
  },
  {
    "name": "Robson",
    "rating": 2
  },
  {
    "name": "Willianson",
    "rating": 2
  },
  {
    "name": "Hian",
    "rating": 2
  },
  {
    "name": "Luis Otávio",
    "rating": 5
  },
  {
    "name": "Jogador",
    "rating": 2
  }
]